relativedeltafield/__init__.py
relativedeltafield/fields.py
relativedeltafield/forms.py
relativedeltafield/utils.py
django_relativedelta-2.0.0.dist-info/LICENSE
django_relativedelta-2.0.0.dist-info/METADATA
django_relativedelta-2.0.0.dist-info/WHEEL
django_relativedelta-2.0.0.dist-info/top_level.txt
django_relativedelta-2.0.0.dist-info/RECORD
